README.md
pyproject.toml
setup.cfg
setup.py
spacetower_measurement_generation_python_client/__init__.py
spacetower_measurement_generation_python_client/api_client.py
spacetower_measurement_generation_python_client/api_response.py
spacetower_measurement_generation_python_client/configuration.py
spacetower_measurement_generation_python_client/exceptions.py
spacetower_measurement_generation_python_client/py.typed
spacetower_measurement_generation_python_client/rest.py
spacetower_measurement_generation_python_client.egg-info/PKG-INFO
spacetower_measurement_generation_python_client.egg-info/SOURCES.txt
spacetower_measurement_generation_python_client.egg-info/dependency_links.txt
spacetower_measurement_generation_python_client.egg-info/requires.txt
spacetower_measurement_generation_python_client.egg-info/top_level.txt
spacetower_measurement_generation_python_client/api/__init__.py
spacetower_measurement_generation_python_client/api/default_api.py
spacetower_measurement_generation_python_client/models/__init__.py
spacetower_measurement_generation_python_client/models/anomaly_type.py
spacetower_measurement_generation_python_client/models/az_el_measurements_request.py
spacetower_measurement_generation_python_client/models/azimuth_elevation_measurements.py
spacetower_measurement_generation_python_client/models/earth_centered_frame_id.py
spacetower_measurement_generation_python_client/models/earth_ellipsoid_configuration.py
spacetower_measurement_generation_python_client/models/earth_fixed_frame_id.py
spacetower_measurement_generation_python_client/models/ellipsoid_id.py
spacetower_measurement_generation_python_client/models/field_description.py
spacetower_measurement_generation_python_client/models/gps_nmea_measurements.py
spacetower_measurement_generation_python_client/models/gps_nmea_measurements_request.py
spacetower_measurement_generation_python_client/models/ground_station.py
spacetower_measurement_generation_python_client/models/inertial_frame_id.py
spacetower_measurement_generation_python_client/models/measurement_request.py
spacetower_measurement_generation_python_client/models/measurement_type.py
spacetower_measurement_generation_python_client/models/measurements_generation_request.py
spacetower_measurement_generation_python_client/models/measurements_generation_result.py
